CoordinateTransformations/RP2T.py
CoordinateTransformations/R_x.py
CoordinateTransformations/R_y.py
CoordinateTransformations/R_z.py
CoordinateTransformations/Screw_X.py
CoordinateTransformations/Screw_Z.py
CoordinateTransformations/T2RP.py
CoordinateTransformations/T_translation.py
CoordinateTransformations/T_x.py
CoordinateTransformations/T_y.py
CoordinateTransformations/T_z.py
CoordinateTransformations/__init__.py
CoordinateTransformations/axis_angle2rotation.py
CoordinateTransformations/axis_angle2transform.py
CoordinateTransformations/cartesian2cylinderical.py
CoordinateTransformations/cartesian2spherical.py
CoordinateTransformations/compound_rotations.py
CoordinateTransformations/compound_rotations_v2.py
CoordinateTransformations/compound_transforms.py
CoordinateTransformations/compound_transforms_v2.py
CoordinateTransformations/cylindrical2cartesian.py
CoordinateTransformations/cylindrical2spherical.py
CoordinateTransformations/euler2rotation.py
CoordinateTransformations/euler2transform.py
CoordinateTransformations/inverse_rotation.py
CoordinateTransformations/inverse_transform.py
CoordinateTransformations/pure_translation.py
CoordinateTransformations/rotation2axis_angle.py
CoordinateTransformations/rotation2euler.py
CoordinateTransformations/rotation2transform.py
CoordinateTransformations/rotation_operator.py
CoordinateTransformations/spherical2cartesian.py
CoordinateTransformations/spherical2cylindrical.py
CoordinateTransformations/transform2axis_angle.py
CoordinateTransformations/transform2euler.py
CoordinateTransformations/transform2rotation.py
CoordinateTransformations/transform2translation_vec.py
CoordinateTransformations/transform_operator.py
CoordinateTransformations-0.9.0.dist-info/LICENSE
CoordinateTransformations-0.9.0.dist-info/METADATA
CoordinateTransformations-0.9.0.dist-info/WHEEL
CoordinateTransformations-0.9.0.dist-info/top_level.txt
CoordinateTransformations-0.9.0.dist-info/RECORD
