Metadata-Version: 2.1
Name: CoordinateTransformations
Version: 0.9.0
Summary: UNKNOWN
Home-page: UNKNOWN
Author: Parth Viradiya
Author-email: parthviradiya08@gmail.com
License: MIT
Keywords: robotics,coordinate transformations,robot kinematics
Platform: UNKNOWN
Requires-Dist: numpy (>1.5)
Provides-Extra: dev
Requires-Dist: pytest (>=3.7) ; extra == 'dev'
